controlresell_connector/__init__.py
controlresell_connector/py.typed
controlresell_connector/com/controlresell/connector/models/accounts/Account.py
controlresell_connector/com/controlresell/connector/models/accounts/AccountLabels.py
controlresell_connector/com/controlresell/connector/models/accounts/AccountPlatform.py
controlresell_connector/com/controlresell/connector/models/accounts/CreateAccountPayload.py
controlresell_connector/com/controlresell/connector/models/accounts/UpdateAccountPayload.py
controlresell_connector/com/controlresell/connector/models/accounts/VmExtendRequest.py
controlresell_connector/com/controlresell/connector/models/accounts/VmStopRequest.py
controlresell_connector/com/controlresell/connector/models/accounts/credentials/ShopifyCredentials.py
controlresell_connector/com/controlresell/connector/models/accounts/credentials/VintedCredentials.py
controlresell_connector/com/controlresell/connector/models/application/ControlResellConnectorEnvironment.py
controlresell_connector/com/controlresell/connector/models/application/PlatformRabbitMQRoutingKey.py
controlresell_connector/com/controlresell/connector/models/jobs/GenericJobError.py
controlresell_connector/com/controlresell/connector/models/jobs/JobRequest.py
controlresell_connector/com/controlresell/connector/models/jobs/JobResponseWebhook.py
controlresell_connector/com/controlresell/connector/models/jobs/accounts/activity/JobAccountsHumanActivityPayload.py
controlresell_connector/com/controlresell/connector/models/jobs/accounts/activity/JobAccountsHumanActivityResponse.py
controlresell_connector/com/controlresell/connector/models/jobs/accounts/ping/JobAccountsPingError.py
controlresell_connector/com/controlresell/connector/models/jobs/accounts/ping/JobAccountsPingPayload.py
controlresell_connector/com/controlresell/connector/models/jobs/accounts/ping/JobAccountsPingResponse.py
controlresell_connector/com/controlresell/connector/models/jobs/auth/data/JobAuthDataResponse.py
controlresell_connector-0.2.23.dist-info/METADATA
controlresell_connector-0.2.23.dist-info/WHEEL
controlresell_connector-0.2.23.dist-info/top_level.txt
controlresell_connector-0.2.23.dist-info/RECORD
