Metadata-Version: 2.4
Name: controlresell-connector
Version: 0.2.23
Summary: Auto-generated Pydantic project from Kotlin using guimauvedigital/zodable
Requires-Python: >=3.9
Requires-Dist: pydantic
Requires-Dist: zodable-idschema
Requires-Dist: uuid
Requires-Dist: typing
Requires-Dist: datetime
